ofdskit/__init__.py
ofdskit/cli/__init__.py
ofdskit/cli/__main__.py
ofdskit/lib/__init__.py
ofdskit/lib/geojson.py
ofdskit-0.1.0.dist-info/LICENSE
ofdskit-0.1.0.dist-info/METADATA
ofdskit-0.1.0.dist-info/WHEEL
ofdskit-0.1.0.dist-info/entry_points.txt
ofdskit-0.1.0.dist-info/top_level.txt
ofdskit-0.1.0.dist-info/RECORD
